{
  "name": "deletable",
  "version": "0.0.2",
  "entities": {
    "item": {
      "schema": {
        "type": "object",
        "properties": {
          "id": {
            "type": "string",
            "x-zui": {}
          }
        },
        "required": ["id"],
        "additionalProperties": false,
        "x-zui": {},
        "$schema": "http://json-schema.org/draft-07/schema#"
      }
    }
  },
  "events": {
    "deleted": {
      "schema": {
        "type": "object",
        "properties": {
          "id": {
            "type": "string",
            "x-zui": {}
          }
        },
        "required": ["id"],
        "additionalProperties": false,
        "x-zui": {},
        "$schema": "http://json-schema.org/draft-07/schema#"
      }
    }
  },
  "actions": {
    "delete": {
      "input": {
        "schema": {
          "type": "object",
          "properties": {
            "id": {
              "type": "string",
              "x-zui": {}
            }
          },
          "required": ["id"],
          "additionalProperties": false,
          "x-zui": {},
          "$schema": "http://json-schema.org/draft-07/schema#"
        }
      },
      "output": {
        "schema": {
          "type": "object",
          "properties": {},
          "additionalProperties": false,
          "x-zui": {},
          "$schema": "http://json-schema.org/draft-07/schema#"
        }
      }
    }
  },
  "channels": {}
}
